synology_drive_api/base.py
synology_drive_api/drive.py
synology_drive_api/files.py
synology_drive_api/labels.py
synology_drive_api/tasks.py
synology_drive_api/utils.py
synology_drive_api-1.0.15.dist-info/LICENSE
synology_drive_api-1.0.15.dist-info/WHEEL
synology_drive_api-1.0.15.dist-info/METADATA
synology_drive_api-1.0.15.dist-info/RECORD
