Metadata-Version: 2.1
Name: synology-drive-api
Version: 1.0.15
Summary: synology drive api python wrapper
Home-page: https://github.com/zbjdonald/synology-drive-api
License: MIT
Keywords: synology,synology-drive
Author: zbjdonald
Author-email: zbjdonald@qq.com
Requires-Python: >=3.7,<4.0
Classifier: License :: OSI Approved :: MIT License
Classifier: Programming Language :: Python :: 3
Classifier: Programming Language :: Python :: 3.10
Classifier: Programming Language :: Python :: 3.7
Classifier: Programming Language :: Python :: 3.8
Classifier: Programming Language :: Python :: 3.9
Requires-Dist: optionaldict (>=0.1.1,<0.2.0)
Requires-Dist: requests (>=2.22.0,<3.0.0)
Requires-Dist: selenium (>=3.141.0,<4.0.0)
Requires-Dist: simplejson
Project-URL: Repository, https://github.com/zbjdonald/synology-drive-api
